config_py/__init__.py
config_py/bin/__init__.py
config_py/bin/config_py.py
config_py/fixtures/__init__.py
config_py/fixtures/config_dev.py
config_py/lib/__init__.py
config_py-0.1.1.dist-info/DESCRIPTION.rst
config_py-0.1.1.dist-info/METADATA
config_py-0.1.1.dist-info/RECORD
config_py-0.1.1.dist-info/WHEEL
config_py-0.1.1.dist-info/entry_points.txt
config_py-0.1.1.dist-info/metadata.json
config_py-0.1.1.dist-info/top_level.txt
version/__init__.py
