Metadata-Version: 2.0
Name: config-py
Version: 0.1.1
Summary: A Python package for managing configuration files in your apps
Home-page: https://github.com/pavloo/config_py
Author: Pavlo Osadchyi
Author-email: posadchiy@gmail.com
License: MIT
Platform: UNKNOWN
Classifier: Development Status :: 4 - Beta
Classifier: Intended Audience :: Developers
Classifier: License :: OSI Approved :: MIT License
Classifier: Programming Language :: Python :: 3
Requires-Dist: click (>=6.7)
